odoo8_addon_account_fiscal_year_reopen-8.0.1.0.0.99.dev11-py3.8-nspkg.pth
odoo_addons/account_fiscal_year_reopen/README.rst
odoo_addons/account_fiscal_year_reopen/__init__.py
odoo_addons/account_fiscal_year_reopen/__openerp__.py
odoo_addons/account_fiscal_year_reopen/i18n/account_fiscal_year_reopen.pot
odoo_addons/account_fiscal_year_reopen/i18n/ca.po
odoo_addons/account_fiscal_year_reopen/i18n/de.po
odoo_addons/account_fiscal_year_reopen/i18n/es.po
odoo_addons/account_fiscal_year_reopen/i18n/fr.po
odoo_addons/account_fiscal_year_reopen/i18n/it.po
odoo_addons/account_fiscal_year_reopen/i18n/pt.po
odoo_addons/account_fiscal_year_reopen/i18n/pt_BR.po
odoo_addons/account_fiscal_year_reopen/i18n/pt_PT.po
odoo_addons/account_fiscal_year_reopen/i18n/sl.po
odoo_addons/account_fiscal_year_reopen/models/__init__.py
odoo_addons/account_fiscal_year_reopen/models/account_fiscalyear.py
odoo_addons/account_fiscal_year_reopen/static/description/icon.png
odoo_addons/account_fiscal_year_reopen/views/account_fiscalyear.xml
odoo8_addon_account_fiscal_year_reopen-8.0.1.0.0.99.dev11.dist-info/METADATA
odoo8_addon_account_fiscal_year_reopen-8.0.1.0.0.99.dev11.dist-info/WHEEL
odoo8_addon_account_fiscal_year_reopen-8.0.1.0.0.99.dev11.dist-info/namespace_packages.txt
odoo8_addon_account_fiscal_year_reopen-8.0.1.0.0.99.dev11.dist-info/top_level.txt
odoo8_addon_account_fiscal_year_reopen-8.0.1.0.0.99.dev11.dist-info/RECORD
